jax_enums/__init__.py
jax_enums/_version.py
jax_enums/enum.py
jax_enums-0.1.2.dist-info/AUTHORS
jax_enums-0.1.2.dist-info/LICENSE
jax_enums-0.1.2.dist-info/METADATA
jax_enums-0.1.2.dist-info/NOTICE
jax_enums-0.1.2.dist-info/WHEEL
jax_enums-0.1.2.dist-info/top_level.txt
jax_enums-0.1.2.dist-info/RECORD
