Metadata-Version: 2.1
Name: jax-enums
Version: 0.1.2
Summary: JAX-compatible Enumerations.
Author-email: Eduardo Pignatelli <edu.pignatelli@gmail.com>
Maintainer-email: Eduardo Pignatelli <edu.pignatelli@gmail.com>
License: Apache License
Project-URL: homepage, https://github.com/epignatelli/jax_enums
Project-URL: repository, https://github.com/epignatelli/jax_enums
Project-URL: bug_tracker, https://github.com/epignatelli/jax_enums/issues
Classifier: Development Status :: 3 - Alpha
Classifier: Intended Audience :: Developers
Classifier: Intended Audience :: Science/Research
Classifier: Intended Audience :: Financial and Insurance Industry
Classifier: Intended Audience :: Healthcare Industry
Classifier: Environment :: GPU
Classifier: Environment :: GPU :: NVIDIA CUDA
Classifier: Environment :: GPU :: NVIDIA CUDA :: 11.0
Classifier: Environment :: GPU :: NVIDIA CUDA :: 11.1
Classifier: Environment :: GPU :: NVIDIA CUDA :: 11.2
Classifier: Environment :: GPU :: NVIDIA CUDA :: 11.3
Classifier: Environment :: GPU :: NVIDIA CUDA :: 11.4
Classifier: Environment :: GPU :: NVIDIA CUDA :: 11.5
Classifier: Environment :: GPU :: NVIDIA CUDA :: 11.6
Classifier: Environment :: GPU :: NVIDIA CUDA :: 11.7
Classifier: Environment :: GPU :: NVIDIA CUDA :: 11.8
Classifier: Framework :: Pytest
Classifier: License :: OSI Approved :: Apache Software License
Classifier: Operating System :: OS Independent
Classifier: Programming Language :: Python
Classifier: Programming Language :: Python :: 3
Classifier: Programming Language :: Python :: 3.9
Classifier: Programming Language :: Python :: 3.10
Classifier: Programming Language :: Python :: 3.11
Classifier: Topic :: Scientific/Engineering
Classifier: Topic :: Scientific/Engineering :: Artificial Intelligence
Classifier: Topic :: Software Development
Classifier: Topic :: Software Development :: Libraries
Classifier: Topic :: Software Development :: Libraries :: Python Modules
Requires-Python: >=3.9
License-File: LICENSE
License-File: NOTICE
License-File: AUTHORS
Requires-Dist: typing-extensions
Requires-Dist: jax
Requires-Dist: jaxlib
Requires-Dist: pytest
